fifa_pack/__init__.py
fifa_pack/extract_att.py
fifa_pack/extract_deep.py
fifa_pack/extract_def.py
fifa_pack/extract_goalkeep.py
fifa_pack/extract_mentality.py
fifa_pack/extract_move.py
fifa_pack/extract_pow.py
fifa_pack/extract_skill.py
fifa_pack/extract_stats.py
fifa_pack/flatten.py
fifa_pack/multi_threading.py
fifa_pack/pipeline.py
fifa_pack/save_csv.py
fifa_pack-0.0.3.dist-info/LICENSE
fifa_pack-0.0.3.dist-info/WHEEL
fifa_pack-0.0.3.dist-info/METADATA
fifa_pack-0.0.3.dist-info/RECORD
